<?xml version="1.0" encoding="utf-8"?>
<HardwareManager xmlns:xsi="http://www.w3.org/2001/XMLSchema-instance" xmlns:xsd="http://www.w3.org/2001/XMLSchema">
  <BroadcastTimeChanges>false</BroadcastTimeChanges>
  <Mgi Enabled="false">
    <PollingInterval>PT0.2S</PollingInterval>
    <GPIO />
    <DviLevelShifters />
    <Transceivers />
    <DefaultBacklightValue>-1</DefaultBacklightValue>
  </Mgi>
  <GPS>
    <ConnectionType>GpsPilot</ConnectionType>
  </GPS>
  <SNTP Enabled="false" Version="3" Host="192.168.135.6" UpdateInterval="PT23H59M59.999S" />
  <VDV301 ValidateHttpRequests="false" ValidateHttpResponses="false" VerifyVersion="false" Enabled="false" DeviceClass="InteriorDisplay">
    <TimeSync Enabled="false" Version="3" />
  </VDV301>
  <Settings>
    <Setting>
      <Conditions />
      <HostnameSource>MacAddress</HostnameSource>
      <TimeZone>Central Standard Time</TimeZone>
      <Display Mode="Clone">
        <Screens></Screens>
      </Display>
    </Setting>
  </Settings>
</HardwareManager>


